MANIFEST.in
README.rst
setup.cfg
setup.py
modeldeploy_proxy_controller/__init__.py
modeldeploy_proxy_controller/cli.py
modeldeploy_proxy_controller.egg-info/PKG-INFO
modeldeploy_proxy_controller.egg-info/SOURCES.txt
modeldeploy_proxy_controller.egg-info/dependency_links.txt
modeldeploy_proxy_controller.egg-info/entry_points.txt
modeldeploy_proxy_controller.egg-info/not-zip-safe
modeldeploy_proxy_controller.egg-info/requires.txt
modeldeploy_proxy_controller.egg-info/top_level.txt
modeldeploy_proxy_controller/common/__init__.py
modeldeploy_proxy_controller/common/logutils.py
modeldeploy_proxy_controller/common/utils.py
modeldeploy_proxy_controller/processors/__init__.py
modeldeploy_proxy_controller/processors/nbprocessor.py
modeldeploy_proxy_controller/res/transformer.ipynb
modeldeploy_proxy_controller/rpc/errors.py
modeldeploy_proxy_controller/rpc/log.py
modeldeploy_proxy_controller/rpc/nb.py
modeldeploy_proxy_controller/rpc/proxy.py
modeldeploy_proxy_controller/rpc/run.py
modeldeploy_proxy_controller/rpc/utils.py